funcpipe/__init__.py
funcpipe/stream.py
functional_piped-0.1.0.dist-info/LICENSE
functional_piped-0.1.0.dist-info/METADATA
functional_piped-0.1.0.dist-info/WHEEL
functional_piped-0.1.0.dist-info/top_level.txt
functional_piped-0.1.0.dist-info/RECORD
