Metadata-Version: 2.1
Name: functional-piped
Version: 0.1.0
Summary: Write s(iterator).map(func) instead of map(func, iterator)
Home-page: https://github.com/Vopaaz/functional-piped
Author: Vopaaz
Author-email: liyifan945@gmail.com
Classifier: Programming Language :: Python :: 3.9
Classifier: Programming Language :: Python :: 3.10
Classifier: Programming Language :: Python :: 3.11
Classifier: Programming Language :: Python :: 3.12
Classifier: License :: OSI Approved :: MIT License
Requires-Python: >=3.9
License-File: LICENSE
